Metadata-Version: 2.1
Name: uecauth
Version: 0.0.10
Summary: UEC Auth
Home-page: https://github.com/uec-world-dominators/uecauth
Author: shosatojp
Author-email: me@shosato.jp
License: Type license() to see the full license text
Platform: UNKNOWN
Classifier: Programming Language :: Python :: 3
Requires-Python: >=3.6
